maksim_132/__init__.py
maksim_132/maksim_132.py
maksim_132/mousecolor.py
maksim_132-0.1.5.dist-info/licenses/LICENSE
maksim_132-0.1.5.dist-info/METADATA
maksim_132-0.1.5.dist-info/WHEEL
maksim_132-0.1.5.dist-info/top_level.txt
maksim_132-0.1.5.dist-info/RECORD
