Metadata-Version: 2.4
Name: maksim_132
Version: 0.1.5
Summary: Library for detecting user location and sending to Telegram bot
Author-email: Maksim <your.email@example.com>
License: © 2024 Beginning_Package
Classifier: License :: OSI Approved :: MIT License
Classifier: Programming Language :: Python :: 3
Classifier: Operating System :: OS Independent
License-File: LICENSE
Requires-Dist: requests>=2.25.0
Dynamic: license-file
